README.md
setup.py
misclib/__init__.py
misclib/latex2utf.py
misclib/misc.py
postproclib/OF_field_parser.py
postproclib/OF_mesh_parser.py
postproclib/__init__.py
postproclib/allpostproc.py
postproclib/build_vmd_polymer_psf.py
postproclib/cfdfields.py
postproclib/cfdpostproc.py
postproclib/cfdrawdata.py
postproclib/channelflowfields.py
postproclib/channelflowpostproc.py
postproclib/channelflowrawdata.py
postproclib/cplfields.py
postproclib/cplpostproc.py
postproclib/exceptions.py
postproclib/field.py
postproclib/headerdata.py
postproclib/lammpsfields.py
postproclib/lammpspostproc.py
postproclib/lammpsrawdata.py
postproclib/mdfields.py
postproclib/mdmacroprops.py
postproclib/mdmols.py
postproclib/mdpostproc.py
postproclib/mdrawdata.py
postproclib/openfoamfields.py
postproclib/openfoampostproc.py
postproclib/openfoamrawdata.py
postproclib/postproc.py
postproclib/pplexceptions.py
postproclib/psiboilrawdata.py
postproclib/rawdata.py
postproclib/serial_cfdfields.py
postproclib/serial_cfdpostproc.py
postproclib/serial_cfdrawdata.py
postproclib/vmd_reformat.py
postproclib/vmdfields.py
postproclib/writecolormap.py
postproclib/visualiser/__init__.py
postproclib/visualiser/choosefield.py
postproclib/visualiser/directory.py
postproclib/visualiser/mainframe.py
postproclib/visualiser/mathtext_wx.py
postproclib/visualiser/minimalscript.py
postproclib/visualiser/plot.py
postproclib/visualiser/script.py
postproclib/visualiser/sliders.py
postproclib/visualiser/visuals.py
pyDataView.egg-info/PKG-INFO
pyDataView.egg-info/SOURCES.txt
pyDataView.egg-info/dependency_links.txt
pyDataView.egg-info/entry_points.txt
pyDataView.egg-info/requires.txt
pyDataView.egg-info/top_level.txt