Metadata-Version: 2.1
Name: pyDataView
Version: 2.0.2
Summary: Data Viewer GUI written in python, wxpython and matplotlib
Home-page: https://github.com/edwardsmith999/pyDataView
Author: ['Edward Smith']
Author-email: edward.smith@brunel.ac.uk
License: GPL
Keywords: visualisation scientific data
Platform: UNKNOWN
Classifier: Development Status :: 3 - Alpha
Classifier: Programming Language :: Python :: 3.6
Provides-Extra: Channelflow_plots
Provides-Extra: cpl_plots
